pytest_pydantic_schema_sync-0.2.1.dist-info/METADATA
pytest_pydantic_schema_sync-0.2.1.dist-info/WHEEL
pytest_pydantic_schema_sync-0.2.1.dist-info/entry_points.txt
pytest_pydantic_schema_sync/__init__.py
pytest_pydantic_schema_sync/config.py
pytest_pydantic_schema_sync/data_model.py
pytest_pydantic_schema_sync/plugin.py
pytest_pydantic_schema_sync-0.2.1.dist-info/RECORD
