Metadata-Version: 2.1
Name: pytest-pydantic-schema-sync
Version: 0.2.1
Summary: Pytest plugin to synchronise Pydantic model schemas with JSONSchema files
Author-Email: Louis Maddox <louismmx@gmail.com>
License: MIT
Project-URL: Homepage, https://github.com/lmmx/pydantic-schema-sync/packages/pytest-pydantic-schema-sync
Project-URL: Repository, https://github.com/lmmx/pydantic-schema-sync.git
Requires-Python: >=3.10
Requires-Dist: pydantic-schema-sync>=0.1.5
Requires-Dist: pytest>=6
